README.md
setup.py
riskModel/EDA.py
riskModel/FeatureEngineering.py
riskModel/Modeling.py
riskModel/Preprocessing.py
riskModel/RiskStragety.py
riskModel/__init__.py
riskModel.egg-info/PKG-INFO
riskModel.egg-info/SOURCES.txt
riskModel.egg-info/dependency_links.txt
riskModel.egg-info/requires.txt
riskModel.egg-info/top_level.txt
riskModel/data/__init__.py
riskModel/data/german.txt
riskModel/data/germancredit.csv
riskModel/data/germancredit.py
riskModel/utils/PltFunction.py
riskModel/utils/__init__.py
riskModel/utils/tools.py
riskModel/utils/btl/__init__.py
riskModel/utils/btl/merge.py
riskModel/utils/btl/monotous.py