Metadata-Version: 1.0
Name: riskModel
Version: 1.0.5
Summary: build credit score model
Home-page: https://github.com/huangxianyang/risk-model
Author: huangsir
Author-email: hxysir@163.com
License: MIT License
Keywords: pip,EDA,Preprocessing,FeatureEngineering,Modeling,RiskStragety
Platform: any
